LICENSE.txt
README.rst
keypad.py
setup.py
micropython_simple_keypad.egg-info/PKG-INFO
micropython_simple_keypad.egg-info/SOURCES.txt
micropython_simple_keypad.egg-info/dependency_links.txt
micropython_simple_keypad.egg-info/top_level.txt