Metadata-Version: 2.1
Name: micropython-simple-keypad
Version: 1.0.2
Summary: MicroPython library for interfacing with a keypad matrix
Home-page: https://github.com/PerfecXX/MicroPython-Keypad
Author: Teeraphat Kullanankanjana
Author-email: ku.teeraphat@hotmail.com
Maintainer: Teeraphat Kullanankanjana
Maintainer-email: ku.teeraphat@hotmail.com
License: MIT
Keywords: keypad,esp32,esp8266,micropython
Platform: UNKNOWN
Classifier: Development Status :: 3 - Alpha
Classifier: Programming Language :: Python :: Implementation :: MicroPython
Classifier: License :: OSI Approved :: MIT License
License-File: LICENSE.txt
